amos_api.py
utils.py
amos_api-1.0.9.dist-info/METADATA
amos_api-1.0.9.dist-info/WHEEL
amos_api-1.0.9.dist-info/top_level.txt
amos_api-1.0.9.dist-info/RECORD
