Metadata-Version: 2.4
Name: amos_api
Version: 1.0.9
Summary: AMOS common api
Author-email: "ilex.h" <390132625@qq.com>, leavor <lint.hit@163.com>
Project-URL: Homepage, https://github.com/aptray/python-pkg
Classifier: Programming Language :: Python :: 3
Classifier: License :: OSI Approved :: GNU General Public License v3 (GPLv3)
Classifier: Operating System :: OS Independent
Requires-Python: >=3
Requires-Dist: pydantic<3.0.0,>=2.0.0
